{
  "sailnumber": "NED/NED1031",
  "country": "NED",
  "name": "Batfish",
  "rating": {
    "gph": 609.4,
    "osn": 590.5,
    "triple_offshore": [
      0.8572,
      1.1133,
      1.2513
    ],
    "triple_inshore": [
      0.6631,
      0.899,
      1.0189
    ]
  },
  "boat": {
    "builder": "JPK COMPOSITES",
    "type": "JPK 10.30",
    "designer": "VALER JACQUES",
    "year": 2019,
    "sizes": {
      "loa": 10.313,
      "beam": 3.23,
      "draft": 2.0,
      "displacement": 3901.0,
      "genoa": 28.41,
      "main": 33.67,
      "spinnaker": 0.0,
      "spinnaker_asym": 108.94,
      "crew": 520.0,
      "wetted_surface": 25.14
    },
    "stability_index": 114.8
  },
  "vpp": {
    "angles": [
      52,
      60,
      75,
      90,
      110,
      120,
      135,
      150
    ],
    "speeds": [
      4,
      6,
      8,
      10,
      12,
      14,
      16,
      20,
      24
    ],
    "52": [
      3.85,
      5.22,
      6.22,
      6.86,
      7.19,
      7.32,
      7.4,
      7.48,
      7.45
    ],
    "60": [
      4.09,
      5.49,
      6.46,
      7.05,
      7.38,
      7.55,
      7.65,
      7.77,
      7.75
    ],
    "75": [
      4.22,
      5.7,
      6.72,
      7.24,
      7.55,
      7.85,
      8.06,
      8.3,
      8.4
    ],
    "90": [
      4.46,
      5.96,
      6.98,
      7.53,
      7.9,
      8.14,
      8.32,
      8.79,
      9.09
    ],
    "110": [
      4.38,
      5.96,
      7.09,
      7.72,
      8.24,
      8.59,
      9.02,
      9.73,
      10.25
    ],
    "120": [
      4.25,
      5.83,
      7.0,
      7.67,
      8.26,
      8.83,
      9.34,
      10.32,
      11.46
    ],
    "135": [
      3.62,
      5.16,
      6.46,
      7.3,
      7.88,
      8.48,
      9.13,
      10.85,
      13.33
    ],
    "150": [
      3.04,
      4.34,
      5.51,
      6.52,
      7.28,
      7.76,
      8.25,
      9.41,
      12.53
    ],
    "beat_angle": [
      43.6,
      43.6,
      41.3,
      39.6,
      38.5,
      38.2,
      38.7,
      39.1,
      40.6
    ],
    "beat_vmg": [
      2.45,
      3.42,
      4.21,
      4.75,
      5.04,
      5.15,
      5.22,
      5.25,
      5.13
    ],
    "run_angle": [
      142.8,
      142.8,
      146.9,
      148.2,
      152.1,
      154.8,
      154.1,
      144.8,
      142.8
    ],
    "run_vmg": [
      2.63,
      3.76,
      4.77,
      5.65,
      6.32,
      6.76,
      7.17,
      8.15,
      10.85
    ]
  }
}