{
  "sailnumber": "GRE/GRE4954",
  "country": "GRE",
  "name": "AELLA",
  "rating": {
    "gph": 618.7,
    "osn": 600.7,
    "triple_offshore": [
      0.8482,
      1.0961,
      1.2145
    ],
    "triple_inshore": [
      0.6556,
      0.8905,
      1.0154
    ]
  },
  "boat": {
    "builder": "BENETEAU",
    "type": "FIRST 41 S5",
    "designer": "BERRET",
    "year": 1988,
    "sizes": {
      "loa": 12.3,
      "beam": 3.9,
      "draft": 1.99,
      "displacement": 7890.0,
      "genoa": 40.44,
      "main": 45.8,
      "spinnaker": 123.79,
      "spinnaker_asym": 0.0,
      "crew": 400.0,
      "wetted_surface": 31.04
    },
    "stability_index": -1.0
  },
  "vpp": {
    "angles": [
      52,
      60,
      75,
      90,
      110,
      120,
      135,
      150
    ],
    "speeds": [
      4,
      6,
      8,
      10,
      12,
      14,
      16,
      20,
      24
    ],
    "52": [
      3.96,
      5.32,
      6.27,
      6.85,
      7.15,
      7.28,
      7.35,
      7.43,
      7.42
    ],
    "60": [
      4.23,
      5.62,
      6.55,
      7.09,
      7.37,
      7.52,
      7.59,
      7.69,
      7.71
    ],
    "75": [
      4.42,
      5.84,
      6.76,
      7.28,
      7.59,
      7.78,
      7.91,
      8.07,
      8.17
    ],
    "90": [
      4.32,
      5.76,
      6.72,
      7.29,
      7.64,
      7.89,
      8.1,
      8.4,
      8.59
    ],
    "110": [
      4.25,
      5.8,
      6.93,
      7.54,
      7.9,
      8.17,
      8.34,
      8.65,
      8.91
    ],
    "120": [
      4.13,
      5.67,
      6.81,
      7.49,
      7.91,
      8.26,
      8.58,
      9.02,
      9.38
    ],
    "135": [
      3.61,
      5.08,
      6.3,
      7.19,
      7.71,
      8.11,
      8.49,
      9.3,
      10.4
    ],
    "150": [
      2.91,
      4.2,
      5.38,
      6.45,
      7.26,
      7.73,
      8.12,
      8.89,
      9.88
    ],
    "beat_angle": [
      44.1,
      44.1,
      41.8,
      40.8,
      40.3,
      39.9,
      39.8,
      39.9,
      41
    ],
    "beat_vmg": [
      2.51,
      3.46,
      4.19,
      4.66,
      4.91,
      5.03,
      5.09,
      5.13,
      5.04
    ],
    "run_angle": [
      137.7,
      137.7,
      149.2,
      149.6,
      157.9,
      164.9,
      170.9,
      177.1,
      173.9
    ],
    "run_vmg": [
      2.52,
      3.64,
      4.66,
      5.58,
      6.4,
      7.0,
      7.47,
      8.19,
      8.91
    ]
  }
}