{
  "sailnumber": "GRE/GRE6238",
  "country": "GRE",
  "name": "ESTELLA",
  "rating": {
    "gph": 614.4,
    "osn": 594.9,
    "triple_offshore": [
      0.84,
      1.1102,
      1.2449
    ],
    "triple_inshore": [
      0.6461,
      0.8968,
      1.037
    ]
  },
  "boat": {
    "builder": "BENETEAU",
    "type": "FIRST 42 S7",
    "designer": "BRUCE FARR",
    "year": 1993,
    "sizes": {
      "loa": 12.688,
      "beam": 4.13,
      "draft": 1.78,
      "displacement": 8500.0,
      "genoa": 46.8,
      "main": 45.24,
      "spinnaker": 113.21,
      "spinnaker_asym": 0.0,
      "crew": 765.0,
      "wetted_surface": 34.72
    },
    "stability_index": 107.7
  },
  "vpp": {
    "angles": [
      52,
      60,
      75,
      90,
      110,
      120,
      135,
      150
    ],
    "speeds": [
      4,
      6,
      8,
      10,
      12,
      14,
      16,
      20,
      24
    ],
    "52": [
      3.89,
      5.3,
      6.35,
      7.01,
      7.36,
      7.53,
      7.61,
      7.68,
      7.68
    ],
    "60": [
      4.22,
      5.66,
      6.67,
      7.26,
      7.59,
      7.76,
      7.84,
      7.94,
      7.96
    ],
    "75": [
      4.44,
      5.91,
      6.89,
      7.46,
      7.79,
      8.01,
      8.16,
      8.34,
      8.44
    ],
    "90": [
      4.3,
      5.79,
      6.84,
      7.47,
      7.84,
      8.1,
      8.33,
      8.68,
      8.89
    ],
    "110": [
      4.08,
      5.66,
      6.9,
      7.62,
      8.04,
      8.36,
      8.63,
      9.0,
      9.29
    ],
    "120": [
      3.94,
      5.49,
      6.73,
      7.53,
      8.0,
      8.38,
      8.73,
      9.37,
      9.81
    ],
    "135": [
      3.46,
      4.91,
      6.16,
      7.12,
      7.74,
      8.15,
      8.54,
      9.36,
      10.34
    ],
    "150": [
      2.83,
      4.12,
      5.31,
      6.36,
      7.21,
      7.75,
      8.15,
      8.9,
      9.77
    ],
    "beat_angle": [
      45.4,
      45.4,
      43.6,
      41.7,
      40.8,
      40.2,
      39.9,
      40,
      41
    ],
    "beat_vmg": [
      2.44,
      3.39,
      4.17,
      4.73,
      5.05,
      5.2,
      5.27,
      5.31,
      5.24
    ],
    "run_angle": [
      144.8,
      144.8,
      148.7,
      150.7,
      156.1,
      163.2,
      169.1,
      177.2,
      176.3
    ],
    "run_vmg": [
      2.45,
      3.57,
      4.6,
      5.51,
      6.32,
      6.96,
      7.48,
      8.23,
      8.92
    ]
  }
}