{
  "sailnumber": "ITA/ITA40002",
  "country": "ITA",
  "name": "HAURAKI",
  "rating": {
    "gph": 534.8,
    "osn": 521.6,
    "triple_offshore": [
      1.0128,
      1.2471,
      1.3966
    ],
    "triple_inshore": [
      0.7964,
      1.0209,
      1.1614
    ]
  },
  "boat": {
    "builder": "Starmarine",
    "type": "Millenium 40 R",
    "designer": "Lostuzzi",
    "year": 2003,
    "sizes": {
      "loa": 11.936,
      "beam": 4.02,
      "draft": 2.74,
      "displacement": 5698.0,
      "genoa": 43.12,
      "main": 59.67,
      "spinnaker": 0.0,
      "spinnaker_asym": 182.34,
      "crew": 600.0,
      "wetted_surface": 31.49
    },
    "stability_index": 123.3
  },
  "vpp": {
    "angles": [
      52,
      60,
      75,
      90,
      110,
      120,
      135,
      150
    ],
    "speeds": [
      4,
      6,
      8,
      10,
      12,
      14,
      16,
      20,
      24
    ],
    "52": [
      4.83,
      6.37,
      7.3,
      7.69,
      7.87,
      7.98,
      8.07,
      8.19,
      8.17
    ],
    "60": [
      5.13,
      6.66,
      7.52,
      7.9,
      8.09,
      8.23,
      8.34,
      8.49,
      8.52
    ],
    "75": [
      5.35,
      6.86,
      7.66,
      8.1,
      8.41,
      8.63,
      8.8,
      9.05,
      9.17
    ],
    "90": [
      5.19,
      6.74,
      7.62,
      8.12,
      8.55,
      8.92,
      9.22,
      9.67,
      9.99
    ],
    "110": [
      5.23,
      6.86,
      7.87,
      8.41,
      8.82,
      9.18,
      9.53,
      10.18,
      10.95
    ],
    "120": [
      5.07,
      6.75,
      7.86,
      8.53,
      9.11,
      9.57,
      10.02,
      10.93,
      11.82
    ],
    "135": [
      4.4,
      6.14,
      7.48,
      8.22,
      8.92,
      9.7,
      10.59,
      12.28,
      13.97
    ],
    "150": [
      3.66,
      5.15,
      6.42,
      7.45,
      8.17,
      8.8,
      9.5,
      11.49,
      15.02
    ],
    "beat_angle": [
      41.7,
      41.7,
      39.4,
      37.7,
      36.8,
      36.4,
      36.4,
      36.5,
      37.8
    ],
    "beat_vmg": [
      3.13,
      4.25,
      5.05,
      5.44,
      5.64,
      5.76,
      5.84,
      5.92,
      5.81
    ],
    "run_angle": [
      141.9,
      141.9,
      145.3,
      150.3,
      153.4,
      151.4,
      148.6,
      145.3,
      147.3
    ],
    "run_vmg": [
      3.17,
      4.46,
      5.56,
      6.45,
      7.12,
      7.63,
      8.22,
      9.95,
      13.01
    ]
  }
}